setup.py
sqlent/__init__.py
sqlent/helpers.py
sqlent/query.py
sqlent.egg-info/PKG-INFO
sqlent.egg-info/SOURCES.txt
sqlent.egg-info/dependency_links.txt
sqlent.egg-info/not-zip-safe
sqlent.egg-info/top_level.txt
test/test_helpers.py
test/test_main.py
test/test_select.py